STutils/__init__.py
STutils/pl/__init__.py
STutils/pl/_cellbin_plot.py
STutils/pl/_nhood_heatmap.py
STutils/pl/_utils.py
STutils/pp/__init__.py
STutils/pp/_merge_big_cell.py
STutils/tl/__init__.py
STutils/tl/_aucell.py
STutils/tl/_cell_neighboring.py
STutils/tl/_getDEG.py
STutils/tl/_removeBiasGenes.py
stereoutils-0.0.2.dist-info/METADATA
stereoutils-0.0.2.dist-info/WHEEL
stereoutils-0.0.2.dist-info/licenses/LICENSE
stereoutils-0.0.2.dist-info/RECORD
