Metadata-Version: 2.4
Name: StereoUtils
Version: 0.0.2
Summary: scanpy extra function for STOmics
Project-URL: Documentation, https://STutils.readthedocs.io/
Project-URL: Source, https://github.com/ChanghaoGong/STutils
Project-URL: Home-page, https://github.com/ChanghaoGong/STutils
Author: ChanghaoGong
Maintainer-email: ChanghaoGong <gongchanghao@genomics.cn>
License: MIT License
License-File: LICENSE
Requires-Python: >=3.9
Requires-Dist: anndata
Requires-Dist: attrs
Requires-Dist: boltons
Requires-Dist: ctxcore
Requires-Dist: matplotlib
Requires-Dist: matplotlib-scalebar
Requires-Dist: numpy
Requires-Dist: opencv-python
Requires-Dist: pandas
Requires-Dist: scanpy
Requires-Dist: scikit-learn
Requires-Dist: seaborn
Requires-Dist: session-info
Requires-Dist: squidpy
Requires-Dist: tqdm
Requires-Dist: typing
Provides-Extra: dev
Requires-Dist: pre-commit; extra == 'dev'
Requires-Dist: twine>=4.0.2; extra == 'dev'
Provides-Extra: doc
Requires-Dist: docutils!=0.18.*,!=0.19.*,>=0.8; extra == 'doc'
Requires-Dist: ipykernel; extra == 'doc'
Requires-Dist: ipython; extra == 'doc'
Requires-Dist: myst-nb; extra == 'doc'
Requires-Dist: pandas; extra == 'doc'
Requires-Dist: sphinx-autodoc-typehints; extra == 'doc'
Requires-Dist: sphinx-book-theme>=1.0.0; extra == 'doc'
Requires-Dist: sphinx-copybutton; extra == 'doc'
Requires-Dist: sphinx>=4; extra == 'doc'
Requires-Dist: sphinxcontrib-bibtex>=1.0.0; extra == 'doc'
Requires-Dist: sphinxext-opengraph; extra == 'doc'
Provides-Extra: test
Requires-Dist: coverage; extra == 'test'
Requires-Dist: pytest; extra == 'test'
